django_component/__init__.py
django_component/arg_tag.py
django_component/cache.py
django_component/component.py
django_component/component_tag.py
django_component/library.py
django_component/media.py
django_component/templatetags/__init__.py
django_component/templatetags/django_component.py
django_component-0.1.7.dist-info/LICENSE
django_component-0.1.7.dist-info/WHEEL
django_component-0.1.7.dist-info/METADATA
django_component-0.1.7.dist-info/RECORD
