Metadata-Version: 2.1
Name: django-component
Version: 0.1.7
Summary: Django template tags to create composable components
Home-page: https://gitlab.com/Mojeer/django_components
License: MIT
Keywords: django,components,template
Author: Jérôme Bon
Author-email: bon.jerome@protonmail.com
Requires-Python: >=3.6
Classifier: Development Status :: 3 - Alpha
Classifier: Environment :: Web Environment
Classifier: Framework :: Django
Classifier: Intended Audience :: Developers
Classifier: License :: OSI Approved :: MIT License
Classifier: Operating System :: OS Independent
Classifier: Programming Language :: Python
Classifier: Programming Language :: Python :: 3
Classifier: Programming Language :: Python :: 3.6
Classifier: Programming Language :: Python :: 3.7
Classifier: Programming Language :: Python :: 3.8
Classifier: Topic :: Internet :: WWW/HTTP
Classifier: Topic :: Internet :: WWW/HTTP :: Dynamic Content
Requires-Dist: django (>=1.11)
Project-URL: Repository, https://gitlab.com/Mojeer/django_components
